Workbook

Sheet Start here
A1: Holiday Budget Planner
A2: Lumen & Ledger - CC BY 4.0. No macros, no external links, no tracking. Works in Excel, LibreOffice and Google Sheets.
A4: HOW TO USE (yellow cells are inputs, everything else is calculated)
A5: 1. 'Setup': year, your total holiday budget, a budget for each category, and (optional) what you actually spent last year.
A6: 2. 'Gifts': one row per person. Set a budget per person first, then log what you really paid (+ shipping/wrapping for that gift).
A7: The Gifts category budget in Setup is the SUM of the per-person budgets, so planning starts from people, not from a round number.
A8: 3. 'Other spending': food and hosting, travel, decorations, cards and postage, events, donations... one row per purchase.
A9: 4. 'Summary': planned vs actual per category, what is left, change vs last year, gifts per group, and how much went on credit cards.
A11: WHAT THE CHECKS MEAN
A12: - 'Plan vs total budget' in Setup: if your category budgets add up to more than your total budget, the gap is shown in red before you spend.
A13: - Red 'Remaining' = that person or category is over budget.
A14: - Returned a gift? Set status 'Returned' and clear its price (or enter the replacement), otherwise it still counts as spent.
... A26: Free updates and other small tools: https://lumen-ledger.github.io/

Sheet Summary
A1: Summary
A2: ="Year "&Setup!B2
A4: Category | B4: Planned | C4: Actual | D4: Remaining | E4: % used | F4: Last year actual | G4: Change vs last year (so far)
A5: =Setup!A6 | B5: =Setup!B6 | C5: =SUM(Gifts!G2:G151) | D5: =B5-C5 | E5: =IF(N(B5)=0,"",C5/B5) | F5: =IF(Setup!C6="","",Setup!C6) | G5: =IF(F5="","",C5-F5)
A6: =Setup!A7 | B6: =Setup!B7 | C6: =SUMIF('Other spending'!B2:B301,A6,'Other spending'!D2:D301) | D6: =B6-C6 | E6: =IF(N(B6)=0,"",C6/B6) | F6: =IF(Setup!C7="","",Setup!C7) | G6: =IF(F6="","",C6-F6)
A7: =Setup!A8 | B7: =Setup!B8 | C7: =SUMIF('Other spending'!B2:B301,A7,'Other spending'!D2:D301) | D7: =B7-C7 | E7: =IF(N(B7)=0,"",C7/B7) | F7: =IF(Setup!C8="","",Setup!C8) | G7: =IF(F7="","",C7-F7)
A8: =Setup!A9 | B8: =Setup!B9 | C8: =SUMIF('Other spending'!B2:B301,A8,'Other spending'!D2:D301) | D8: =B8-C8 | E8: =IF(N(B8)=0,"",C8/B8) | F8: =IF(Setup!C9="","",Setup!C9) | G8: =IF(F8="","",C8-F8)
A9: =Setup!A10 | B9: =Setup!B10 | C9: =SUMIF('Other spending'!B2:B301,A9,'Other spending'!D2:D301) | D9: =B9-C9 | E9: =IF(N(B9)=0,"",C9/B9) | F9: =IF(Setup!C10="","",Setup!C10) | G9: =IF(F9="","",C9-F9)
A10: =Setup!A11 | B10: =Setup!B11 | C10: =SUMIF('Other spending'!B2:B301,A10,'Other spending'!D2:D301) | D10: =B10-C10 | E10: =IF(N(B10)=0,"",C10/B10) | F10: =IF(Setup!C11="","",Setup!C11) | G10: =IF(F10="","",C10-F10)
A11: =Setup!A12 | B11: =Setup!B12 | C11: =SUMIF('Other spending'!B2:B301,A11,'Other spending'!D2:D301) | D11: =B11-C11 | E11: =IF(N(B11)=0,"",C11/B11) | F11: =IF(Setup!C12="","",Setup!C12) | G11: =IF(F11="","",C11-F11)
A12: =Setup!A13 | B12: =Setup!B13 | C12: =SUMIF('Other spending'!B2:B301,A12,'Other spending'!D2:D301) | D12: =B12-C12 | E12: =IF(N(B12)=0,"",C12/B12) | F12: =IF(Setup!C13="","",Setup!C13) | G12: =IF(F12="","",C12-F12)
A13: =Setup!A14 | B13: =Setup!B14 | C13: =SUMIF('Other spending'!B2:B301,A13,'Other spending'!D2:D301) | D13: =B13-C13 | E13: =IF(N(B13)=0,"",C13/B13) | F13: =IF(Setup!C14="","",Setup!C14) | G13: =IF(F13="","",C13-F13)
A14: Total | B14: =SUM(B5:B13) | C14: =SUM(C5:C13) | D14: =B14-C14 | E14: =IF(N(B14)=0,"",C14/B14) | F14: =SUM(F5:F13) | G14: =IF(F14=0,"",C14-F14)
A16: Against your total budget
A17: Total budget (Setup) | B17: =Setup!B3
A18: Spent so far (all rows) | B18: =SUM(Gifts!G2:G151)+SUM('Other spending'!D2:D301)
A19: Left to spend | B19: =Setup!B3-B18
A20: % of total budget used | B20: =IF(N(Setup!B3)=0,"",B18/Setup!B3)
A21: Other spending with no category (fix it) | B21: =B18-C14
A22: Charged to credit cards (Gifts + Other) | B22: =SUMIF(Gifts!K2:K151,Setup!A21,Gifts!G2:G151)+SUMIF('Other spending'!E2:E301,Setup!A21,'Other spending'!D2:D301)
A24: Gifts by group
A25: Group | B25: People | C25: Budget | D25: Spent | E25: Remaining
A26: Family | B26: =COUNTIF(Gifts!B2:B151,A26) | C26: =SUMIF(Gifts!B2:B151,A26,Gifts!C2:C151) | D26: =SUMIF(Gifts!B2:B151,A26,Gifts!G2:G151) | E26: =C26-D26
A27: Kids | B27: =COUNTIF(Gifts!B2:B151,A27) | C27: =SUMIF(Gifts!B2:B151,A27,Gifts!C2:C151) | D27: =SUMIF(Gifts!B2:B151,A27,Gifts!G2:G151) | E27: =C27-D27
A28: Friends | B28: =COUNTIF(Gifts!B2:B151,A28) | C28: =SUMIF(Gifts!B2:B151,A28,Gifts!C2:C151) | D28: =SUMIF(Gifts!B2:B151,A28,Gifts!G2:G151) | E28: =C28-D28
A29: Work | B29: =COUNTIF(Gifts!B2:B151,A29) | C29: =SUMIF(Gifts!B2:B151,A29,Gifts!C2:C151) | D29: =SUMIF(Gifts!B2:B151,A29,Gifts!G2:G151) | E29: =C29-D29
A30: Hosts | B30: =COUNTIF(Gifts!B2:B151,A30) | C30: =SUMIF(Gifts!B2:B151,A30,Gifts!C2:C151) | D30: =SUMIF(Gifts!B2:B151,A30,Gifts!G2:G151) | E30: =C30-D30
A31: Other | B31: =COUNTIF(Gifts!B2:B151,A31) | C31: =SUMIF(Gifts!B2:B151,A31,Gifts!C2:C151) | D31: =SUMIF(Gifts!B2:B151,A31,Gifts!G2:G151) | E31: =C31-D31
A33: Gift status
A34: Status | B34: Gifts
A35: Idea | B35: =COUNTIF(Gifts!I2:I151,A35)
A36: Ordered | B36: =COUNTIF(Gifts!I2:I151,A36)
A37: Bought | B37: =COUNTIF(Gifts!I2:I151,A37)
A38: Wrapped | B38: =COUNTIF(Gifts!I2:I151,A38)
A39: Given | B39: =COUNTIF(Gifts!I2:I151,A39)
A40: Returned | B40: =COUNTIF(Gifts!I2:I151,A40)
A41: People with no status yet | B41: =COUNTA(Gifts!A2:A151)-COUNTA(Gifts!I2:I151)

Sheet Setup
A1: Setup
A2: Year | B2: 2026
A3: Total holiday budget | B3: 1500 | D3: The most you want to spend on the whole season, all categories.
A5: Category | B5: Planned | C5: Last year actual (optional) | D5: Notes
A6: Gifts | B6: =SUM(Gifts!C2:C151) | C6: 820 | D6: Calculated: sum of per-person budgets in 'Gifts'.
A7: Food & hosting | B7: 300 | C7: 340
A8: Travel | B8: 250 | C8: 0
A9: Decorations | B9: 60 | C9: 95
A10: Cards & postage | B10: 25 | C10: 30
A11: Wrapping & shipping | B11: 30 | C11: 45
A12: Events & outings | B12: 80 | C12: 60
A13: Donations | B13: 100 | C13: 100
A14: Other | B14: 50 | C14: 70
A15: Total planned | B15: =SUM(B6:B14) | C15: =SUM(C6:C14)
A16: Plan vs total budget (positive = room left) | B16: =B3-B15 | D16: Red = your category budgets add up to more than the total. Cut a category or raise the total.
A18: Payment methods (edit the names if you like)
A19: Cash
A20: Debit card
A21: Credit card | D21: Summary totals 'Charged to credit cards' from the 3rd name in this list.
A22: Gift card / points
A23: Other

Sheet Gifts
A1: Recipient | B1: Group | C1: Budget | D1: Gift idea | E1: Price paid | F1: Shipping / wrap (this gift) | G1: Total | H1: Remaining | I1: Status | J1: Bought where | K1: Paid with | L1: Return by | M1: Notes
A2: Example: Mom | B2: Family | C2: 120 | D2: Cookbook + apron | E2: 64.5 | F2: 6.99 | G2: =IF(AND(E2="",F2=""),"",N(E2)+N(F2)) | H2: =IF(C2="","",C2-N(G2)) | I2: Bought | J2: Bookstore | K2: Credit card | L2: 46387
A3: Example: Sam | B3: Kids | C3: 80 | D3: Building set | E3: 74.99 | F3: 0 | G3: =IF(AND(E3="",F3=""),"",N(E3)+N(F3)) | H3: =IF(C3="","",C3-N(G3)) | I3: Wrapped | J3: Online shop | K3: Debit card | L3: 46402
A4: Example: Alex | B4: Friends | C4: 40 | D4: Board game | E4: 46 | F4: 4.5 | G4: =IF(AND(E4="",F4=""),"",N(E4)+N(F4)) | H4: =IF(C4="","",C4-N(G4)) | I4: Ordered | J4: Online shop | K4: Credit card
A5: Example: Team | B5: Work | C5: 30 | D5: Snack box | G5: =IF(AND(E5="",F5=""),"",N(E5)+N(F5)) | H5: =IF(C5="","",C5-N(G5)) | I5: Idea
G6: =IF(AND(E6="",F6=""),"",N(E6)+N(F6)) | H6: =IF(C6="","",C6-N(G6))
G7: =IF(AND(E7="",F7=""),"",N(E7)+N(F7)) | H7: =IF(C7="","",C7-N(G7))
G8: =IF(AND(E8="",F8=""),"",N(E8)+N(F8)) | H8: =IF(C8="","",C8-N(G8))
G9: =IF(AND(E9="",F9=""),"",N(E9)+N(F9)) | H9: =IF(C9="","",C9-N(G9))
G10: =IF(AND(E10="",F10=""),"",N(E10)+N(F10)) | H10: =IF(C10="","",C10-N(G10))
G11: =IF(AND(E11="",F11=""),"",N(E11)+N(F11)) | H11: =IF(C11="","",C11-N(G11))
G12: =IF(AND(E12="",F12=""),"",N(E12)+N(F12)) | H12: =IF(C12="","",C12-N(G12))
G13: =IF(AND(E13="",F13=""),"",N(E13)+N(F13)) | H13: =IF(C13="","",C13-N(G13))
G14: =IF(AND(E14="",F14=""),"",N(E14)+N(F14)) | H14: =IF(C14="","",C14-N(G14))
G15: =IF(AND(E15="",F15=""),"",N(E15)+N(F15)) | H15: =IF(C15="","",C15-N(G15))
G16: =IF(AND(E16="",F16=""),"",N(E16)+N(F16)) | H16: =IF(C16="","",C16-N(G16))
G17: =IF(AND(E17="",F17=""),"",N(E17)+N(F17)) | H17: =IF(C17="","",C17-N(G17))
... G151: =IF(AND(E151="",F151=""),"",N(E151)+N(F151)) | H151: =IF(C151="","",C151-N(G151))

Sheet Other spending
A1: Date | B1: Category | C1: What | D1: Amount | E1: Paid with | F1: Notes
A2: 46354 | B2: Decorations | C2: Example: lights + wreath | D2: 42 | E2: Debit card
A3: 46358 | B3: Cards & postage | C3: Example: 20 cards + stamps | D3: 31.4 | E3: Cash
A4: 46376 | B4: Food & hosting | C4: Example: dinner groceries | D4: 186.25 | E4: Credit card
A5: 46379 | B5: Travel | C5: Example: train tickets | D5: 128 | E5: Credit card
